src/cli.py
src/example.py
src/limerick_generator.py
ozgrav_limerick_generator-1.2.0.dist-info/METADATA
ozgrav_limerick_generator-1.2.0.dist-info/WHEEL
ozgrav_limerick_generator-1.2.0.dist-info/entry_points.txt
ozgrav_limerick_generator-1.2.0.dist-info/RECORD
