Metadata-Version: 2.3
Name: ozgrav-limerick-generator
Version: 1.2.0
Summary: A Python module that connects to OpenAI's ChatGPT API to generate humorous limericks on any topic
Author: Owen Cole
Author-email: ocole@swin.edu.au
Requires-Python: >=3.12,<4.0
Classifier: Programming Language :: Python :: 3
Classifier: Programming Language :: Python :: 3.12
Classifier: Programming Language :: Python :: 3.13
Requires-Dist: openai (>=1.0.0,<2.0.0)
Requires-Dist: pyyaml (>=6.0,<7.0)
